mkdocs_vwidref
