Metadata-Version: 2.1
Name: mkdocs-vwidref
Version: 1.0.21
Summary: MkDocs plugin to link by front-matter ID with status/progress/title flags ([[id:s|p|t:...]]).
Home-page: UNKNOWN
Author: Your Name
License: MIT
Keywords: mkdocs plugin wiki interwiki frontmatter idref
Platform: UNKNOWN
Classifier: Framework :: MkDocs
Classifier: Programming Language :: Python :: 3
Classifier: License :: OSI Approved :: MIT License
Classifier: Operating System :: OS Independent
Requires-Python: >=3.8
License-File: LICENSE
